homie_helpers/__init__.py
homie_helpers/device.py
homie_helpers/properties.py
homie_helpers/test_device.py
homie_helpers-0.0.7.dist-info/LICENSE
homie_helpers-0.0.7.dist-info/METADATA
homie_helpers-0.0.7.dist-info/WHEEL
homie_helpers-0.0.7.dist-info/top_level.txt
homie_helpers-0.0.7.dist-info/RECORD
