Metadata-Version: 2.1
Name: homie-helpers
Version: 0.0.7
Summary: A set of helpers for implementing Homie IoT Convention
Home-page: https://github.com/rzarajczyk/homie-helpers
Author: Rafał Zarajczyk
Author-email: rzarajczyk@gmail.com
Keywords: HOMIE,MQTT
Classifier: Programming Language :: Python :: 3
Classifier: License :: OSI Approved :: MIT License
Classifier: Operating System :: OS Independent
License-File: LICENSE
Requires-Dist: paho-mqtt (>=1.3.0)
Requires-Dist: Homie4 (>=0.3.8)
